pySVCGAL/__init__.py
pySVCGAL/pySVCGAL.py
pySVCGAL/clib/__init__.py
pySVCGAL/clib/ctSVCGAL.dll
pySVCGAL/clib/libctSVCGAL.dylib
pySVCGAL/clib/libctSVCGAL.so
pySVCGAL/clib/load_library.py
pysvcgal-0.0.25.dist-info/METADATA
pysvcgal-0.0.25.dist-info/WHEEL
pysvcgal-0.0.25.dist-info/licenses/LICENSE
pysvcgal-0.0.25.dist-info/RECORD
