Metadata-Version: 2.4
Name: pySVCGAL
Version: 0.0.25
Summary: Python CGAL straight skeleton extrude wrapper
Project-URL: Homepage, https://github.com/satabol/pySVCGAL
Project-URL: Issues, https://github.com/satabol/pySVCGAL/issues
Author-email: Satabol <satabol@yandex.ru>
License-File: LICENSE
Keywords: extrude,skeleton
Classifier: Development Status :: 2 - Pre-Alpha
Classifier: Intended Audience :: Developers
Classifier: Operating System :: Microsoft :: Windows
Classifier: Operating System :: Unix
Classifier: Programming Language :: Python :: 3
Requires-Python: >=3.8
Requires-Dist: more-itertools
